lis_simplelogger/__init__.py
lis_simplelogger/lis_simplelogger.py
lis_simplelogger-0.2.0.dist-info/LICENSE
lis_simplelogger-0.2.0.dist-info/METADATA
lis_simplelogger-0.2.0.dist-info/WHEEL
lis_simplelogger-0.2.0.dist-info/top_level.txt
lis_simplelogger-0.2.0.dist-info/RECORD
