Metadata-Version: 2.1
Name: lis-simplelogger
Version: 0.2.0
Summary: Simple Logger for LIS.
Home-page: https://github.com/timothyjchun/lis-simplelogger
Author: Timothy Chun
Author-email: timchun0212@gmail.com
License: MIT
Classifier: Programming Language :: Python :: 3
Classifier: License :: OSI Approved :: MIT License
Classifier: Operating System :: OS Independent
Requires-Python: >=3.6
License-File: LICENSE
